MANIFEST.in
README.md
requirements.txt
setup.py
src/specter_warden.egg-info/PKG-INFO
src/specter_warden.egg-info/SOURCES.txt
src/specter_warden.egg-info/dependency_links.txt
src/specter_warden.egg-info/not-zip-safe
src/specter_warden.egg-info/requires.txt
src/specter_warden.egg-info/top_level.txt
src/warden/__init__.py
src/warden/__main__.py
src/warden/backgroundjobs.py
src/warden/config.ini
src/warden/config.py
src/warden/debug.log.1
src/warden/debug.log.2
src/warden/logo.py
src/warden/routes.py
src/warden/specter_controller_api.py
src/warden/trash.html
src/warden/utils.py
src/warden/version.txt
src/warden/warden_decorators.py
src/warden/warden_modules.py
src/warden/warden_pricing_engine.py
src/warden/__pycache__/__init__.cpython-37.pyc
src/warden/__pycache__/__init__.cpython-38.pyc
src/warden/__pycache__/__main__.cpython-37.pyc
src/warden/__pycache__/backgroundjobs.cpython-37.pyc
src/warden/__pycache__/config.cpython-37.pyc
src/warden/__pycache__/config.cpython-38.pyc
src/warden/__pycache__/logo.cpython-37.pyc
src/warden/__pycache__/routes.cpython-37.pyc
src/warden/__pycache__/routes.cpython-38.pyc
src/warden/__pycache__/utils.cpython-37.pyc
src/warden/__pycache__/warden.cpython-37.pyc
src/warden/__pycache__/warden.cpython-38.pyc
src/warden/__pycache__/warden_decorators.cpython-37.pyc
src/warden/__pycache__/warden_decorators.cpython-38.pyc
src/warden/__pycache__/warden_modules.cpython-37.pyc
src/warden/__pycache__/warden_pricing_engine.cpython-37.pyc
src/warden/__pycache__/warden_pricing_engine.cpython-38.pyc
src/warden/errors/__init__.py
src/warden/errors/handlers.py
src/warden/errors/__pycache__/__init__.cpython-37 2.pyc
src/warden/errors/__pycache__/__init__.cpython-37 3.pyc
src/warden/errors/__pycache__/__init__.cpython-37.pyc
src/warden/errors/__pycache__/__init__.cpython-38.pyc
src/warden/errors/__pycache__/handlers.cpython-37.pyc
src/warden/errors/__pycache__/handlers.cpython-38.pyc
src/warden/static/config/config_default.ini
src/warden/static/config/version.txt
src/warden/static/css/warden_layout.css
src/warden/static/css/warden_main.css
src/warden/static/csv_files/digital_currency_list.csv
src/warden/static/csv_files/physical_currency_list.csv
