Metadata-Version: 2.1
Name: specter-warden
Version: 0.6.0.6
Summary: Private Portfolio Tool - Specter Server Edition
Home-page: https://github.com/pxsocs/specter_warden
Author: Alpha Zeta
Author-email: alphaazeta@protonmail.com
License: UNKNOWN
Platform: UNKNOWN
Classifier: Programming Language :: Python :: 3
Classifier: License :: OSI Approved :: MIT License
Classifier: Operating System :: OS Independent
Classifier: Framework :: Flask
Requires-Python: >=3.6
